{
  "phase": 1,
  "stage": 1,
  "current_item": "drive-iec",
  "stage1_remaining": [],
  "retry_count": 0,
  "max_retries": 4,
  "ts_runtime_root": "/Users/alex/Development/C64/Tools/C64ReverseEngineeringMCP",
  "ts_spec_root": "/Users/alex/Development/C64/Tools/C64ReverseEngineeringMCP/src/runtime",
  "done": [
    "oracle-harness",
    "core-substrate",
    "cpu-6510",
    "vic-ii",
    "cia"
  ],
  "in_flight": null,
  "note": "Stage 1 SERIAL (ADR-014): cia(core) merged. Next: drive-iec [sonnet], last Stage-1 chip. cia-cascade tracked (ADR-017).",
  "updated": "2026-06-22T18:46:00Z",
  "followups": [
    "cia-cascade"
  ]
}
